airflow_lark_provider/__init__.py
airflow_lark_provider/get_provider_info.py
airflow_lark_provider/hooks/__init__.py
airflow_lark_provider/hooks/lark_webhook_hook.py
airflow_lark_provider/operators/__init__.py
airflow_lark_provider/operators/lark_webhook_operator.py
airflow_lark_provider/sensors/__init__.py
airflow_lark_provider/utils/__init__.py
airflow_lark_provider-1.0.0.dist-info/licenses/LICENSE
docs/__init__.py
tests/__init__.py
tests/test_lark_webhook_hook.py
tests/test_lark_webhook_operator.py
airflow_lark_provider-1.0.0.dist-info/METADATA
airflow_lark_provider-1.0.0.dist-info/WHEEL
airflow_lark_provider-1.0.0.dist-info/entry_points.txt
airflow_lark_provider-1.0.0.dist-info/top_level.txt
airflow_lark_provider-1.0.0.dist-info/RECORD
