Metadata-Version: 2.4
Name: airflow-lark-provider
Version: 1.0.0
Summary: Lark (Feishu) integration for Apache Airflow
Home-page: https://github.com/yourusername/airflow-lark-provider
Author: Your Name
Author-email: Your Name <your.email@example.com>
Maintainer-email: Your Name <your.email@example.com>
License: MIT
Project-URL: Homepage, https://github.com/yourusername/airflow-lark-provider
Project-URL: Documentation, https://github.com/yourusername/airflow-lark-provider/blob/main/README.md
Project-URL: Repository, https://github.com/yourusername/airflow-lark-provider
Project-URL: Bug Tracker, https://github.com/yourusername/airflow-lark-provider/issues
Keywords: airflow,lark,feishu,webhook,notification
Classifier: Development Status :: 4 - Beta
Classifier: Environment :: Plugins
Classifier: Intended Audience :: Developers
Classifier: Intended Audience :: System Administrators
Classifier: License :: OSI Approved :: MIT License
Classifier: Programming Language :: Python :: 3
Classifier: Programming Language :: Python :: 3.8
Classifier: Programming Language :: Python :: 3.9
Classifier: Programming Language :: Python :: 3.10
Classifier: Programming Language :: Python :: 3.11
Classifier: Programming Language :: Python :: 3.12
Classifier: Topic :: System :: Monitoring
Classifier: Framework :: Apache Airflow
Classifier: Framework :: Apache Airflow :: Provider
Requires-Python: >=3.8
License-File: LICENSE
Requires-Dist: apache-airflow>=2.0.0
Requires-Dist: requests>=2.20.0
Provides-Extra: dev
Requires-Dist: pytest>=6.0; extra == "dev"
Requires-Dist: pytest-cov; extra == "dev"
Requires-Dist: black; extra == "dev"
Requires-Dist: flake8; extra == "dev"
Requires-Dist: mypy; extra == "dev"
Provides-Extra: test
Requires-Dist: pytest>=6.0; extra == "test"
Requires-Dist: pytest-cov; extra == "test"
Requires-Dist: pytest-mock; extra == "test"
Dynamic: author
Dynamic: home-page
Dynamic: license-file
Dynamic: requires-python
